fswalk/__init__.py
fswalk/main.py
fswalk/workers.py
fswalk-1.3.11.dist-info/LICENSE
fswalk-1.3.11.dist-info/METADATA
fswalk-1.3.11.dist-info/WHEEL
fswalk-1.3.11.dist-info/entry_points.txt
fswalk-1.3.11.dist-info/top_level.txt
fswalk-1.3.11.dist-info/RECORD
