Metadata-Version: 2.1
Name: fswalk
Version: 1.3.11
Summary: An efficient multiprocessing directory walk and search tool
Home-page: https://github.com/bzizou/fs_walk
Author: Bruno Bzeznik
Author-email: Bruno.Bzeznik@univ-grenoble-alpes.fr
License: GNU GPL v3
Platform: UNKNOWN
Classifier: Development Status :: 4 - Beta
Classifier: Operating System :: OS Independent
Classifier: Intended Audience :: Developers
Classifier: Programming Language :: Python
Classifier: Programming Language :: Python :: 3
Classifier: License :: OSI Approved :: GNU General Public License v2 or later (GPLv2+)
Classifier: Topic :: Software Development :: Libraries :: Python Modules
Classifier: Topic :: System :: Clustering
Classifier: Topic :: System :: Filesystems
Classifier: Topic :: Utilities
Requires-Python: >=3.5
Requires-Dist: requests
Requires-Dist: pyjson5
Requires-Dist: elasticsearch
